spTimeHelperPy/TimeHelper.py
spTimeHelperPy/__init__.py
sptimehelperpy-1.0.9.dist-info/METADATA
sptimehelperpy-1.0.9.dist-info/WHEEL
sptimehelperpy-1.0.9.dist-info/licenses/LICENSE
sptimehelperpy-1.0.9.dist-info/RECORD
