Metadata-Version: 2.4
Name: spTimeHelperPy
Version: 1.0.9
Summary: A Python package for easy conversion and handling of time values.
Project-URL: Homepage, https://github.com/krokoreit/spTimeHelperPy
Project-URL: Source Code, https://github.com/krokoreit/spTimeHelperPy
Author-email: krokoreit <krokoreit@gmail.com>
License-Expression: MIT
License-File: LICENSE
Keywords: datetime,datetime format,nano seconds since epoch,time conversion,timestamp,timezone,utc
Classifier: Operating System :: OS Independent
Classifier: Programming Language :: Python :: 3
Requires-Python: >=3.10
Requires-Dist: spargvalidatorpy
Requires-Dist: tzdata
